ecowittweather/__init__.py
ecowittweather/api.py
ecowittweather/const.py
ecowittweather/errors.py
ecowittweather-1.0.0.dist-info/LICENSE
ecowittweather-1.0.0.dist-info/METADATA
ecowittweather-1.0.0.dist-info/WHEEL
ecowittweather-1.0.0.dist-info/top_level.txt
ecowittweather-1.0.0.dist-info/RECORD
