Metadata-Version: 2.1
Name: ecowittweather
Version: 1.0.0
Summary: Ecowitt Weather
Home-page: https://github.com/EcowittWeather/ecowittweather
Author: ecowittweather
Author-email: admin@ecowitt.net
Classifier: Programming Language :: Python :: 3
Classifier: License :: OSI Approved :: MIT License
Classifier: Operating System :: OS Independent
License-File: LICENSE
